LICENSE
authorizenet/__init__.py
authorizenet/client.py
authorizenet/context.py
authorizenet/generator.py
authorizenet/logger.py
authorizenet/operation.py
authorizenet/parser.py
authorizenet/schema.py
authorizenet/serializer.py
authorizenet/typing.py
python_authorizenet-0.2.0.dist-info/LICENSE
python_authorizenet-0.2.0.dist-info/METADATA
python_authorizenet-0.2.0.dist-info/WHEEL
python_authorizenet-0.2.0.dist-info/RECORD
