Metadata-Version: 2.1
Name: python-authorizenet
Version: 0.2.0
Summary: A typed Authorize.Net client using httpx and pydantic.
Home-page: https://github.com/paypossible/python-authorizenet
License: MIT
Keywords: authorizenet,authorize.net,payment,ecommerce
Author: Michael Lavers
Author-email: kolanos@gmail.com
Requires-Python: >=3.9,<4
Classifier: Development Status :: 3 - Alpha
Classifier: Intended Audience :: Developers
Classifier: License :: OSI Approved :: MIT License
Classifier: Programming Language :: Python :: 3
Classifier: Programming Language :: Python :: 3.9
Classifier: Programming Language :: Python :: 3.10
Classifier: Programming Language :: Python :: 3.11
Classifier: Programming Language :: Python :: 3.12
Classifier: Topic :: Software Development :: Build Tools
Requires-Dist: httpx[http2] (>=0)
Requires-Dist: xsdata-pydantic[lxml] (>=24)
Project-URL: Repository, https://github.com/paypossible/python-authorizenet
